store/__init__.py
store/constants.py
store/exceptions.py
store/indexer.py
store/interfaces.py
store/ordering.py
store/predicate.py
store/query.py
store/state.py
store/store.py
store/symbol.py
store/transaction.py
store/util.py
python_store-3.0.3.dist-info/LICENSE
python_store-3.0.3.dist-info/METADATA
python_store-3.0.3.dist-info/WHEEL
python_store-3.0.3.dist-info/top_level.txt
python_store-3.0.3.dist-info/RECORD
