Metadata-Version: 2.1
Name: python-store
Version: 3.0.3
Summary: Pure Python in-memory SQL-like object store
Home-page: https://github.com/gigaquads/store
Author: Gigaquads
Author-email: what@gigaquads.com
License: MIT License
Platform: any
Classifier: Programming Language :: Python :: 3.9
Classifier: License :: OSI Approved :: MIT License
Requires-Dist: appyratus
Requires-Dist: ordered-set
Requires-Dist: BTrees
